unique_playgrounds/__init__.py
unique_playgrounds/types_system.py
unique_playgrounds/types_unique.py
unique_playgrounds/unique.py
unique_playgrounds_py-0.0.3.dist-info/LICENSE
unique_playgrounds_py-0.0.3.dist-info/METADATA
unique_playgrounds_py-0.0.3.dist-info/WHEEL
unique_playgrounds_py-0.0.3.dist-info/top_level.txt
unique_playgrounds_py-0.0.3.dist-info/RECORD
